pwdcrk/__init__.py
pwdcrk/pwdcrk.py
pwdcrk-0.0.7.dist-info/METADATA
pwdcrk-0.0.7.dist-info/WHEEL
pwdcrk-0.0.7.dist-info/top_level.txt
pwdcrk-0.0.7.dist-info/RECORD
