Metadata-Version: 2.1
Name: pwdcrk
Version: 0.0.7
Summary: A password cracking tool.
Author: thecarpetjasp
Author-email: thecarpetjasp@gmail.com
Keywords: python,password,password cracker,brute-force,dictionary
Classifier: Development Status :: 1 - Planning
Classifier: Intended Audience :: Developers
Classifier: Programming Language :: Python :: 3
Classifier: Operating System :: Unix
Classifier: Operating System :: MacOS :: MacOS X
Classifier: Operating System :: Microsoft :: Windows
